qs_parser/__init__.py
qs_parser/parser.py
qs_parser/query_key_detail.py
qs_parser/query_params.py
query_parser-0.1.2.dist-info/METADATA
query_parser-0.1.2.dist-info/WHEEL
query_parser-0.1.2.dist-info/RECORD
