Metadata-Version: 2.1
Name: query-parser
Version: 0.1.2
Summary: 
Home-page: https://github.com/quenti77/qs-parser
Author: Quentin Ysambert
Author-email: quentin.ysambert@gmail.com
Requires-Python: >=3.11,<4.0
Classifier: Programming Language :: Python :: 3
Classifier: Programming Language :: Python :: 3.11
Project-URL: Repository, https://github.com/quenti77/qs-parser
